.gitignore
BUGS.md
Dockerfile
HISTORY.md
LICENSE
MANIFEST.in
Makefile
README.md
TODO.md
build_tdigest.py
db_requirements.txt
libraries_help.md
minimal.txt
optional.txt
pyproject.toml
requirements.txt
setup.py
test_requirements.txt
c_source/tdigest/LICENSE
c_source/tdigest/tdigest.c
c_source/tdigest/tdigest.h
deps/Cerberus-1.3.4-py3-none-any.whl
dkit/__init__.py
dkit/base.py
dkit/compatibility.py
dkit/decorators.py
dkit/exceptions.py
dkit/messages.py
dkit/multi_processing.py
dkit/typing_helper.py
dkit/algorithms/__init__.py
dkit/algorithms/tdigest.py
dkit/algorithms/trie.py
dkit/data/__init__.py
dkit/data/aggregation.py
dkit/data/bencode.py
dkit/data/bxr.py
dkit/data/console.py
dkit/data/containers.py
dkit/data/diff.py
dkit/data/eda.py
dkit/data/fake_helper.py
dkit/data/filters.py
dkit/data/helpers.py
dkit/data/histogram.py
dkit/data/infer.py
dkit/data/iteration.py
dkit/data/json_utils.py
dkit/data/kafka_utils.py
dkit/data/manipulate.py
dkit/data/map_db.py
dkit/data/matching.py
dkit/data/msgpack_utils.py
dkit/data/stats.c
dkit/data/stats.py
dkit/data/window.py
dkit/data/xml_helper.py
dkit/data/zmqdb.py
dkit/doc/__init__.py
dkit/doc/builder.py
dkit/doc/canned.py
dkit/doc/document.py
dkit/doc/json_renderer.py
dkit/doc/latex.py
dkit/doc/latex_renderer.py
dkit/doc/lorem.py
dkit/doc/pdf_helper.py
dkit/doc/reportlab_renderer.py
dkit/doc/schemas.py
dkit/doc/xlsx_renderer.ppy
dkit/doc2/__init__.py
dkit/doc2/document.py
dkit/doc2/md_to_doc.py
dkit/doc2/rl_helper.py
dkit/doc2/rl_renderer.py
dkit/doc2/rl_styles.py
dkit/etl/__init__.py
dkit/etl/helpers.py
dkit/etl/model.py
dkit/etl/normalize.py
dkit/etl/reader.py
dkit/etl/schema.py
dkit/etl/sink.py
dkit/etl/source.py
dkit/etl/transform.py
dkit/etl/utilities.py
dkit/etl/verifier.py
dkit/etl/writer.py
dkit/etl/extensions/__init__.py
dkit/etl/extensions/ext_arrow.py
dkit/etl/extensions/ext_athena.py
dkit/etl/extensions/ext_avro.py
dkit/etl/extensions/ext_bxr.py
dkit/etl/extensions/ext_dataclass.py
dkit/etl/extensions/ext_dbapi.py
libdkit.egg-info/PKG-INFO
libdkit.egg-info/SOURCES.txt
libdkit.egg-info/dependency_links.txt
libdkit.egg-info/entry_points.txt
libdkit.egg-info/requires.txt
libdkit.egg-info/top_level.txt
