Metadata-Version: 2.2
Name: libdkit
Version: 25.3.5
Summary: Data Processing Toolkit
Author: Cobus Nel
Project-URL: Homepage, https://github.com/cobusn/dkit
Project-URL: Issues, https://github.com/cobusn/dkit/issues
Classifier: Programming Language :: Python :: 3
Classifier: Operating System :: OS Independent
Classifier: License :: OSI Approved :: MIT License
Requires-Python: >=3.11
License-File: LICENSE
Requires-Dist: cffi>=1.4.0
Requires-Dist: boltons
Requires-Dist: cerberus
Requires-Dist: collections_extended
Requires-Dist: cryptography
Requires-Dist: cython
Requires-Dist: inflect
Requires-Dist: jinja2
Requires-Dist: lz4
Requires-Dist: matplotlib
Requires-Dist: mistune
Requires-Dist: openpyxl
Requires-Dist: pdfrw
Requires-Dist: pyarrow
Requires-Dist: pyparsing
Requires-Dist: pyperclip
Requires-Dist: pydantic
Requires-Dist: python-dateutil
Requires-Dist: python-snappy
Requires-Dist: pyyaml
Requires-Dist: reportlab
Requires-Dist: requests
Requires-Dist: sqlalchemy<2.0,>=1.4.46
Requires-Dist: squarify
Requires-Dist: tabulate
Requires-Dist: tdigest
